apache_airflow_flowitems/__init__.py
apache_airflow_flowitems/core.py
apache_airflow_flowitems/decorators.py
apache_airflow_flowitems/py.typed
apache_airflow_flowitems/test_core.py
apache_airflow_flowitems/test_decorators.py
apache_airflow_flowitems/__pycache__/__init__.cpython-39.pyc
apache_airflow_flowitems/__pycache__/core.cpython-39.pyc
apache_airflow_flowitems/__pycache__/decorators.cpython-39.pyc
apache_airflow_flowitems/__pycache__/test_core.cpython-39-pytest-7.2.2.pyc
apache_airflow_flowitems/__pycache__/test_decorators.cpython-39-pytest-7.2.2.pyc
apache_airflow_flowitems-1.0.2.dist-info/LICENSE
apache_airflow_flowitems-1.0.2.dist-info/METADATA
apache_airflow_flowitems-1.0.2.dist-info/WHEEL
apache_airflow_flowitems-1.0.2.dist-info/top_level.txt
apache_airflow_flowitems-1.0.2.dist-info/RECORD
